odoo/addons/purchase_request_to_requisition/README.rst
odoo/addons/purchase_request_to_requisition/__init__.py
odoo/addons/purchase_request_to_requisition/__manifest__.py
odoo/addons/purchase_request_to_requisition/i18n/am.po
odoo/addons/purchase_request_to_requisition/i18n/ar.po
odoo/addons/purchase_request_to_requisition/i18n/bg.po
odoo/addons/purchase_request_to_requisition/i18n/bs.po
odoo/addons/purchase_request_to_requisition/i18n/ca.po
odoo/addons/purchase_request_to_requisition/i18n/ca_ES.po
odoo/addons/purchase_request_to_requisition/i18n/cs.po
odoo/addons/purchase_request_to_requisition/i18n/da.po
odoo/addons/purchase_request_to_requisition/i18n/de.po
odoo/addons/purchase_request_to_requisition/i18n/el_GR.po
odoo/addons/purchase_request_to_requisition/i18n/en_AU.po
odoo/addons/purchase_request_to_requisition/i18n/en_GB.po
odoo/addons/purchase_request_to_requisition/i18n/es.po
odoo/addons/purchase_request_to_requisition/i18n/es_AR.po
odoo/addons/purchase_request_to_requisition/i18n/es_CL.po
odoo/addons/purchase_request_to_requisition/i18n/es_CO.po
odoo/addons/purchase_request_to_requisition/i18n/es_CR.po
odoo/addons/purchase_request_to_requisition/i18n/es_DO.po
odoo/addons/purchase_request_to_requisition/i18n/es_EC.po
odoo/addons/purchase_request_to_requisition/i18n/es_ES.po
odoo/addons/purchase_request_to_requisition/i18n/es_MX.po
odoo/addons/purchase_request_to_requisition/i18n/es_PE.po
odoo/addons/purchase_request_to_requisition/i18n/es_PY.po
odoo/addons/purchase_request_to_requisition/i18n/es_VE.po
odoo/addons/purchase_request_to_requisition/i18n/et.po
odoo/addons/purchase_request_to_requisition/i18n/eu.po
odoo/addons/purchase_request_to_requisition/i18n/fa.po
odoo/addons/purchase_request_to_requisition/i18n/fi.po
odoo/addons/purchase_request_to_requisition/i18n/fr.po
odoo/addons/purchase_request_to_requisition/i18n/fr_CA.po
odoo/addons/purchase_request_to_requisition/i18n/fr_CH.po
odoo/addons/purchase_request_to_requisition/i18n/fr_FR.po
odoo_addon_purchase_request_to_requisition-18.0.1.0.0.5.dist-info/METADATA
odoo_addon_purchase_request_to_requisition-18.0.1.0.0.5.dist-info/WHEEL
odoo_addon_purchase_request_to_requisition-18.0.1.0.0.5.dist-info/top_level.txt
odoo_addon_purchase_request_to_requisition-18.0.1.0.0.5.dist-info/RECORD
